{
    "dataSource": {
        "contextVariables": [
            {
                "id": 0,
                "name": "Session.AccountId",
                "val": "001RO000004KLOwYAO"
            }
        ],
        "orderBy": {
        },
        "type": null,
        "value": {
        }
    },
    "enableLwc": true,
    "isFlex": true,
    "lwc": {
        "DeveloperName": "cfSfiEnergySelfServiceQuickLinksContainer_2_Salesforce",
        "Id": "0RbRO0000007EZp0AM",
        "ManageableState": "unmanaged",
        "MasterLabel": "cfSfiEnergySelfServiceQuickLinksContainer_2_Salesforce",
        "NamespacePrefix": "c"
    },
    "multilanguageSupport": true,
    "osSupport": true,
    "selectableMode": "Multi",
    "sessionVars": [
        {
            "isApi": true,
            "name": "AccountId",
            "val": ""
        },
        {
            "isApi": true,
            "name": "FirstName",
            "val": ""
        },
        {
            "isApi": true,
            "name": "LastName",
            "val": ""
        }
    ],
    "states": [
        {
            "actions": [
            ],
            "childCards": [
                "sfiEnergySelfServiceQuickLinks"
            ],
            "components": {
                "layer-0": {
                    "children": [
                        {
                            "class": "slds-col ",
                            "element": "childCardPreview",
                            "elementLabel": "FlexCard-0",
                            "name": "FlexCard",
                            "property": {
                                "cardName": "sfiEnergySelfServiceQuickLinks",
                                "cardNode": "",
                                "isChildCardTrackingEnabled": false,
                                "parentAttribute": {
                                    "AccountId": "{Session.AccountId}",
                                    "FirstName": "{Session.FirstName}",
                                    "LastName": "{Session.LastName}"
                                },
                                "recordId": "{recordId}",
                                "selectedState": "Active"
                            },
                            "size": {
                                "default": "12",
                                "isResponsive": false
                            },
                            "stateIndex": 0,
                            "styleObject": {
                                "sizeClass": "slds-size_12-of-12"
                            },
                            "type": "element"
                        }
                    ]
                }
            },
            "conditions": {
                "group": [
                ],
                "id": "state-condition-object",
                "isParent": true
            },
            "definedActions": {
                "actions": [
                ]
            },
            "documents": [
            ],
            "fields": [
            ],
            "isSmartAction": false,
            "name": "Active",
            "omniscripts": [
            ],
            "smartAction": {
            },
            "styleObject": {
                "background": {
                    "color": "",
                    "image": "",
                    "position": "",
                    "repeat": "",
                    "size": ""
                },
                "border": {
                    "color": "",
                    "radius": "",
                    "style": "",
                    "type": "",
                    "width": ""
                },
                "class": "slds-m-bottom_x-large ",
                "container": {
                    "class": ""
                },
                "elementStyleProperties": {
                },
                "inlineStyle": "",
                "margin": [
                    {
                        "label": "bottom:x-large",
                        "size": "x-large",
                        "type": "bottom"
                    }
                ],
                "padding": [
                ],
                "size": {
                    "default": "12",
                    "isResponsive": false
                },
                "sizeClass": "slds-size_12-of-12 ",
                "style": "      \n         ",
                "text": {
                    "align": "",
                    "color": ""
                }
            }
        }
    ],
    "theme": "slds",
    "title": "sfiEnergySelfServiceQuickLinksContainer",
    "xmlJson": [
        {
            "@attributes": {
                "targets": "lightning__AppPage",
                "xmlns": "http://soap.sforce.com/2006/04/metadata"
            },
            "property": [
                {
                    "@attributes": {
                        "name": "debug",
                        "type": "Boolean"
                    }
                },
                {
                    "@attributes": {
                        "name": "recordId",
                        "type": "String"
                    }
                }
            ]
        },
        {
            "@attributes": {
                "targets": "lightning__RecordPage",
                "xmlns": "http://soap.sforce.com/2006/04/metadata"
            },
            "property": [
                {
                    "@attributes": {
                        "name": "debug",
                        "type": "Boolean"
                    }
                }
            ]
        },
        {
            "@attributes": {
                "targets": "lightningCommunity__Default",
                "xmlns": "http://soap.sforce.com/2006/04/metadata"
            },
            "property": [
                {
                    "@attributes": {
                        "label": "accountId",
                        "name": "cfAccountId",
                        "type": "String"
                    }
                },
                {
                    "@attributes": {
                        "label": "firstName",
                        "name": "cfFirstName",
                        "type": "String"
                    }
                },
                {
                    "@attributes": {
                        "label": "lastName",
                        "name": "cfLastName",
                        "type": "String"
                    }
                }
            ]
        }
    ],
    "xmlObject": {
        "apiVersion": 56,
        "isExplicitImport": false,
        "isExposed": true,
        "masterLabel": "sfiEnergySelfServiceQuickLinksContainer",
        "runtimeNamespace": "%vlocity_namespace%",
        "targetConfigs": "PHRhcmdldENvbmZpZyAgeG1sbnM9Imh0dHA6Ly9zb2FwLnNmb3JjZS5jb20vMjAwNi8wNC9tZXRhZGF0YSIgdGFyZ2V0cz0ibGlnaHRuaW5nX19BcHBQYWdlIj48cHJvcGVydHkgIG5hbWU9ImRlYnVnIiB0eXBlPSJCb29sZWFuIj48L3Byb3BlcnR5Pjxwcm9wZXJ0eSAgbmFtZT0icmVjb3JkSWQiIHR5cGU9IlN0cmluZyI+PC9wcm9wZXJ0eT48L3RhcmdldENvbmZpZz48dGFyZ2V0Q29uZmlnICB4bWxucz0iaHR0cDovL3NvYXAuc2ZvcmNlLmNvbS8yMDA2LzA0L21ldGFkYXRhIiB0YXJnZXRzPSJsaWdodG5pbmdfX1JlY29yZFBhZ2UiPjxwcm9wZXJ0eSAgbmFtZT0iZGVidWciIHR5cGU9IkJvb2xlYW4iPjwvcHJvcGVydHk+PC90YXJnZXRDb25maWc+PHRhcmdldENvbmZpZyAgeG1sbnM9Imh0dHA6Ly9zb2FwLnNmb3JjZS5jb20vMjAwNi8wNC9tZXRhZGF0YSIgdGFyZ2V0cz0ibGlnaHRuaW5nQ29tbXVuaXR5X19EZWZhdWx0Ij48cHJvcGVydHkgIG5hbWU9ImNmQWNjb3VudElkIiBsYWJlbD0iYWNjb3VudElkIiB0eXBlPSJTdHJpbmciPjwvcHJvcGVydHk+PHByb3BlcnR5ICBuYW1lPSJjZkZpcnN0TmFtZSIgdHlwZT0iU3RyaW5nIiBsYWJlbD0iZmlyc3ROYW1lIj48L3Byb3BlcnR5Pjxwcm9wZXJ0eSAgbmFtZT0iY2ZMYXN0TmFtZSIgdHlwZT0iU3RyaW5nIiBsYWJlbD0ibGFzdE5hbWUiPjwvcHJvcGVydHk+PC90YXJnZXRDb25maWc+",
        "targets": {
            "target": [
                "lightning__AppPage",
                "lightning__RecordPage",
                "lightningCommunity__Default"
            ]
        }
    }
}