[
    {
        "FilterGroup": 0,
        "FilterOperator": "=",
        "FilterValue": "ProgramId",
        "GlobalKey": "EnergyUtilitiesProgramsFindAccountApplicationProgramRelationCustom7459",
        "InputFieldName": "ProgramId",
        "InputObjectName": "ProgramProduct",
        "InputObjectQuerySequence": 1,
        "IsDisabled": false,
        "IsRequiredForUpsert": false,
        "IsUpsertKey": false,
        "Name": "EnergyUtilitiesProgramsFindAccountApplicationProgramRelation",
        "OmniDataTransformationId": {
            "Name": "EnergyUtilitiesProgramsFindAccountApplicationProgramRelation",
            "VlocityDataPackType": "VlocityMatchingKeyObject",
            "VlocityMatchingRecordSourceKey": "OmniDataTransform/EnergyUtilitiesProgramsFindAccountApplicationProgramRelation",
            "VlocityRecordSObjectType": "OmniDataTransform"
        },
        "OutputCreationSequence": 0,
        "OutputFieldName": "ProgramProductIds",
        "OutputObjectName": "json",
        "VlocityDataPackType": "SObject",
        "VlocityRecordSObjectType": "OmniDataTransformItem"
    },
    {
        "FilterGroup": 0,
        "FilterOperator": "=",
        "FilterValue": "\"Active\"",
        "GlobalKey": "EnergyUtilitiesProgramsFindAccountApplicationProgramRelationCustom7323",
        "InputFieldName": "Status",
        "InputObjectName": "ProgramProduct",
        "InputObjectQuerySequence": 1,
        "IsDisabled": false,
        "IsRequiredForUpsert": false,
        "IsUpsertKey": false,
        "Name": "EnergyUtilitiesProgramsFindAccountApplicationProgramRelation",
        "OmniDataTransformationId": {
            "Name": "EnergyUtilitiesProgramsFindAccountApplicationProgramRelation",
            "VlocityDataPackType": "VlocityMatchingKeyObject",
            "VlocityMatchingRecordSourceKey": "OmniDataTransform/EnergyUtilitiesProgramsFindAccountApplicationProgramRelation",
            "VlocityRecordSObjectType": "OmniDataTransform"
        },
        "OutputCreationSequence": 0,
        "OutputFieldName": "ProgramProductIds",
        "OutputObjectName": "json",
        "VlocityDataPackType": "SObject",
        "VlocityRecordSObjectType": "OmniDataTransformItem"
    },
    {
        "FilterGroup": 0,
        "FilterOperator": "=",
        "FilterValue": "AccountId",
        "GlobalKey": "EnergyUtilitiesProgramsFindAccountApplicationProgramRelation17908848602666483",
        "InputFieldName": "IndividualApplication.AccountId",
        "InputObjectName": "IndividualApplicationItem",
        "InputObjectQuerySequence": 2,
        "IsDisabled": false,
        "IsRequiredForUpsert": false,
        "IsUpsertKey": false,
        "Name": "EnergyUtilitiesProgramsFindAccountApplicationProgramRelation",
        "OmniDataTransformationId": {
            "Name": "EnergyUtilitiesProgramsFindAccountApplicationProgramRelation",
            "VlocityDataPackType": "VlocityMatchingKeyObject",
            "VlocityMatchingRecordSourceKey": "OmniDataTransform/EnergyUtilitiesProgramsFindAccountApplicationProgramRelation",
            "VlocityRecordSObjectType": "OmniDataTransform"
        },
        "OutputCreationSequence": 0,
        "OutputFieldName": "IndividualApplicationItem",
        "OutputObjectName": "json",
        "VlocityDataPackType": "SObject",
        "VlocityRecordSObjectType": "OmniDataTransformItem"
    },
    {
        "FilterGroup": 0,
        "FilterOperator": "=",
        "FilterValue": "ProgramProductIds:Id",
        "GlobalKey": "EnergyUtilitiesProgramsFindAccountApplicationProgramRelation6680774017950284",
        "InputFieldName": "RelatedItemId",
        "InputObjectName": "IndividualApplicationItem",
        "InputObjectQuerySequence": 2,
        "IsDisabled": false,
        "IsRequiredForUpsert": false,
        "IsUpsertKey": false,
        "Name": "EnergyUtilitiesProgramsFindAccountApplicationProgramRelation",
        "OmniDataTransformationId": {
            "Name": "EnergyUtilitiesProgramsFindAccountApplicationProgramRelation",
            "VlocityDataPackType": "VlocityMatchingKeyObject",
            "VlocityMatchingRecordSourceKey": "OmniDataTransform/EnergyUtilitiesProgramsFindAccountApplicationProgramRelation",
            "VlocityRecordSObjectType": "OmniDataTransform"
        },
        "OutputCreationSequence": 0,
        "OutputFieldName": "IndividualApplicationItem",
        "OutputObjectName": "json",
        "VlocityDataPackType": "SObject",
        "VlocityRecordSObjectType": "OmniDataTransformItem"
    },
    {
        "FilterGroup": 0,
        "FilterOperator": "LIMIT",
        "FilterValue": "1",
        "GlobalKey": "EnergyUtilitiesProgramsFindAccountApplicationProgramRelation03939972254839885",
        "InputObjectName": "IndividualApplicationItem",
        "InputObjectQuerySequence": 2,
        "IsDisabled": false,
        "IsRequiredForUpsert": false,
        "IsUpsertKey": false,
        "Name": "EnergyUtilitiesProgramsFindAccountApplicationProgramRelation",
        "OmniDataTransformationId": {
            "Name": "EnergyUtilitiesProgramsFindAccountApplicationProgramRelation",
            "VlocityDataPackType": "VlocityMatchingKeyObject",
            "VlocityMatchingRecordSourceKey": "OmniDataTransform/EnergyUtilitiesProgramsFindAccountApplicationProgramRelation",
            "VlocityRecordSObjectType": "OmniDataTransform"
        },
        "OutputCreationSequence": 0,
        "OutputFieldName": "IndividualApplicationItem",
        "OutputObjectName": "json",
        "VlocityDataPackType": "SObject",
        "VlocityRecordSObjectType": "OmniDataTransformItem"
    },
    {
        "FormulaExpression": "ISNOTBLANK(IndividualApplicationItem:Id)",
        "FormulaResultPath": "areRelated",
        "FormulaSequence": 1,
        "GlobalKey": "EnergyUtilitiesProgramsFindAccountApplicationProgramRelation4491256420260914",
        "IsDisabled": false,
        "IsRequiredForUpsert": false,
        "IsUpsertKey": false,
        "Name": "EnergyUtilitiesProgramsFindAccountApplicationProgramRelation",
        "OmniDataTransformationId": {
            "Name": "EnergyUtilitiesProgramsFindAccountApplicationProgramRelation",
            "VlocityDataPackType": "VlocityMatchingKeyObject",
            "VlocityMatchingRecordSourceKey": "OmniDataTransform/EnergyUtilitiesProgramsFindAccountApplicationProgramRelation",
            "VlocityRecordSObjectType": "OmniDataTransform"
        },
        "OutputCreationSequence": 0,
        "OutputFieldName": "Formula",
        "OutputObjectName": "Formula",
        "VlocityDataPackType": "SObject",
        "VlocityRecordSObjectType": "OmniDataTransformItem"
    },
    {
        "DefaultValue": "false",
        "GlobalKey": "EnergyUtilitiesProgramsFindAccountApplicationProgramRelation9108240020974068",
        "InputFieldName": "areRelated",
        "IsDisabled": false,
        "IsRequiredForUpsert": false,
        "IsUpsertKey": false,
        "Name": "EnergyUtilitiesProgramsFindAccountApplicationProgramRelation",
        "OmniDataTransformationId": {
            "Name": "EnergyUtilitiesProgramsFindAccountApplicationProgramRelation",
            "VlocityDataPackType": "VlocityMatchingKeyObject",
            "VlocityMatchingRecordSourceKey": "OmniDataTransform/EnergyUtilitiesProgramsFindAccountApplicationProgramRelation",
            "VlocityRecordSObjectType": "OmniDataTransform"
        },
        "OutputCreationSequence": 1,
        "OutputFieldFormat": "Boolean",
        "OutputFieldName": "areRelated",
        "OutputObjectName": "json",
        "TransformValueMappings": "{\"\":\"\"}",
        "VlocityDataPackType": "SObject",
        "VlocityRecordSObjectType": "OmniDataTransformItem"
    }
]